<?xml version="1.0"?>
<!DOCTYPE hibernate-mapping PUBLIC "-//Hibernate/Hibernate Mapping DTD 3.0//EN"
        "http://www.hibernate.org/dtd/hibernate-mapping-3.0.dtd">
<!-- Generated 2016-7-8 1:31:59 by Hibernate Tools 3.4.0.CR1 -->
<hibernate-mapping>
    <class name="com.ywxt.Domain.Ali.AliCdn" table="ali_cdn">
        <!-- id主键设置 -->
        <id name="id" type="java.lang.Integer">
            <column name="id" not-null="true"/>
            <generator class="identity"/>
        </id>
        <property name="accessKeyId" type="java.lang.String" length="40" not-null="false"/>
        <property name="cdnType" type="java.lang.String" length="30" not-null="false"/>
        <property name="sourceType" type="java.lang.String" length="30"/>
        <property name="domainName" type="java.lang.String" length="100"/>
        <property name="cname" type="java.lang.String" length="100"/>
        <property name="gmtModified" type="java.util.Date" not-null="true"/>
        <property name="gmtCreated" type="java.util.Date" not-null="true"/>
        <property name="description" type="java.lang.String" length="100"/>
        <property name="resourceGroupId" type="java.lang.String" length="30"/>
        <property name="domainStatus" type="java.lang.String" length="20"/>
    </class>
</hibernate-mapping>